cloudipsp/__init__.py
cloudipsp/api.py
cloudipsp/checkout.py
cloudipsp/configuration.py
cloudipsp/exceptions.py
cloudipsp/helpers.py
cloudipsp/order.py
cloudipsp/payment.py
cloudipsp/resources.py
cloudipsp/utils.py
cloudipsp-1.0.4.dist-info/LICENSE
cloudipsp-1.0.4.dist-info/METADATA
cloudipsp-1.0.4.dist-info/WHEEL
cloudipsp-1.0.4.dist-info/top_level.txt
cloudipsp-1.0.4.dist-info/RECORD
