Metadata-Version: 2.1
Name: cloudipsp
Version: 1.0.4
Summary: Python SDK for cloudipsp clients.
Home-page: https://github.com/cloudipsp/python-sdk/
Author: Dmitriy Miroshnikov
License: MIT
Classifier: Environment :: Web Environment
Classifier: Natural Language :: English
Classifier: License :: OSI Approved :: MIT License
Classifier: Operating System :: OS Independent
Classifier: Programming Language :: Python
Classifier: Programming Language :: Python :: 2.7
Classifier: Programming Language :: Python :: 3
Classifier: Programming Language :: Python :: 3.4
Classifier: Programming Language :: Python :: 3.6
Classifier: Programming Language :: Python :: 3.7
Classifier: Programming Language :: Python :: 3.8
Classifier: Programming Language :: Python :: 3.9
Classifier: Programming Language :: Python :: 3.10
License-File: LICENSE
